nami/__init__.py
nami/cli.py
nami/connection.py
nami/util.py
nami/default_templates/README.md
nami/default_templates/rsync_download.bash
nami/default_templates/rsync_upload.bash
nami/default_templates/setup_apptainer.bash
nami/default_templates/setup_aws.bash
nami/default_templates/setup_conda.bash
nami/default_templates/setup_nfs_client.bash
nami/default_templates/setup_nfs_server.bash
nami/default_templates/setup_tmux.bash
nami/default_templates/sync_from_s3.bash
nami/default_templates/sync_to_s3.bash
nami/default_templates/unzip_data.bash
nami/nfs/__init__.py
nami/nfs/nfs.py
nami/transfer/__init__.py
nami/transfer/rsync.py
nami/transfer/s3.py
nami_surf-0.2.9.dist-info/licenses/LICENSE
nami_surf-0.2.9.dist-info/METADATA
nami_surf-0.2.9.dist-info/WHEEL
nami_surf-0.2.9.dist-info/entry_points.txt
nami_surf-0.2.9.dist-info/top_level.txt
nami_surf-0.2.9.dist-info/RECORD
