Metadata-Version: 2.4
Name: nami-surf
Version: 0.2.9
Summary: Node Administration Made Intuitive
Author-email: Alexander Lutsenko <lex.lutsenko@gmail.com>
Project-URL: Homepage, https://github.com/AlexanderLutsenko/nami
Project-URL: Repository, https://github.com/AlexanderLutsenko/nami
Project-URL: Bug Tracker, https://github.com/AlexanderLutsenko/nami/issues
Keywords: ssh,rsync,s3,remote,administration,automation
Classifier: License :: OSI Approved :: MIT License
Classifier: Programming Language :: Python :: 3
Classifier: Operating System :: OS Independent
Requires-Python: >=3.8
License-File: LICENSE
Requires-Dist: PyYAML>=6.0
Requires-Dist: sty>=1.0.0
Dynamic: license-file
